[{"id":"kvg:05043-s1","start":{"x":31.5,"y":18.39}},{"id":"kvg:05043-s2","start":{"x":26.53,"y":43.5}},{"id":"kvg:05043-s3","start":{"x":39.63,"y":18.78}},{"id":"kvg:05043-s4","start":{"x":54.49,"y":27.54}},{"id":"kvg:05043-s5","start":{"x":55.52,"y":27.99}},{"id":"kvg:05043-s6","start":{"x":56.94,"y":36.61}},{"id":"kvg:05043-s7","start":{"x":57.76,"y":45.55}},{"id":"kvg:05043-s8","start":{"x":69.26,"y":47.87}},{"id":"kvg:05043-s9","start":{"x":80.99,"y":53.8}},{"id":"kvg:05043-s10","start":{"x":49.96,"y":57.48}},{"id":"kvg:05043-s11","start":{"x":44.25,"y":21}}]