[{"id":"kvg:0515a-s1","start":{"x":52.46,"y":13.37}},{"id":"kvg:0515a-s2","start":{"x":29.02,"y":19.71}},{"id":"kvg:0515a-s3","start":{"x":77.01,"y":16.25}},{"id":"kvg:0515a-s4","start":{"x":19.75,"y":36.12}},{"id":"kvg:0515a-s5","start":{"x":20.74,"y":39.18}},{"id":"kvg:0515a-s6","start":{"x":34.64,"y":46.98}},{"id":"kvg:0515a-s7","start":{"x":36.52,"y":48.13}},{"id":"kvg:0515a-s8","start":{"x":39.58,"y":63.69}},{"id":"kvg:0515a-s9","start":{"x":44.99,"y":66.75}},{"id":"kvg:0515a-s10","start":{"x":58.24,"y":64.12}}]