[{"id":"kvg:05546-s1","start":{"x":52.86,"y":12.25}},{"id":"kvg:05546-s2","start":{"x":18,"y":27.61}},{"id":"kvg:05546-s3","start":{"x":35.27,"y":31.46}},{"id":"kvg:05546-s4","start":{"x":70.54,"y":28.14}},{"id":"kvg:05546-s5","start":{"x":23,"y":47.5}},{"id":"kvg:05546-s6","start":{"x":25.23,"y":49.4}},{"id":"kvg:05546-s7","start":{"x":45.72,"y":51.43}},{"id":"kvg:05546-s8","start":{"x":61.1,"y":49.37}},{"id":"kvg:05546-s9","start":{"x":39.31,"y":71.82}},{"id":"kvg:05546-s10","start":{"x":41.98,"y":73.23}},{"id":"kvg:05546-s11","start":{"x":43.35,"y":87.9}}]