[{"id":"kvg:0580b-s1","start":{"x":10.5,"y":40.6}},{"id":"kvg:0580b-s2","start":{"x":23.37,"y":13.5}},{"id":"kvg:0580b-s3","start":{"x":11.25,"y":73.53}},{"id":"kvg:0580b-s4","start":{"x":44.11,"y":17.19}},{"id":"kvg:0580b-s5","start":{"x":46.13,"y":19.05}},{"id":"kvg:0580b-s6","start":{"x":46.13,"y":39.44}},{"id":"kvg:0580b-s7","start":{"x":45.22,"y":59.21}},{"id":"kvg:0580b-s8","start":{"x":74.35,"y":14.71}},{"id":"kvg:0580b-s9","start":{"x":75.49,"y":16.58}},{"id":"kvg:0580b-s10","start":{"x":76.35,"y":36.31}},{"id":"kvg:0580b-s11","start":{"x":75.47,"y":57.15}}]