[{"id":"kvg:05870-s1","start":{"x":22.44,"y":12.15}},{"id":"kvg:05870-s2","start":{"x":16.18,"y":29.73}},{"id":"kvg:05870-s3","start":{"x":16.5,"y":64.37}},{"id":"kvg:05870-s4","start":{"x":54.12,"y":10.5}},{"id":"kvg:05870-s5","start":{"x":51.37,"y":19.71}},{"id":"kvg:05870-s6","start":{"x":52.36,"y":28.07}},{"id":"kvg:05870-s7","start":{"x":54.82,"y":31.43}},{"id":"kvg:05870-s8","start":{"x":63.69,"y":34.9}},{"id":"kvg:05870-s9","start":{"x":61.44,"y":48.65}},{"id":"kvg:05870-s10","start":{"x":37.14,"y":45.87}},{"id":"kvg:05870-s11","start":{"x":27.63,"y":79.45}},{"id":"kvg:05870-s12","start":{"x":52.42,"y":65.62}},{"id":"kvg:05870-s13","start":{"x":17.88,"y":96.36}}]