[{"id":"kvg:0589c-s1","start":{"x":19.04,"y":19.33}},{"id":"kvg:0589c-s2","start":{"x":29.15,"y":34.65}},{"id":"kvg:0589c-s3","start":{"x":20.62,"y":20.52}},{"id":"kvg:0589c-s4","start":{"x":50.21,"y":13.47}},{"id":"kvg:0589c-s5","start":{"x":74.9,"y":12.18}},{"id":"kvg:0589c-s6","start":{"x":42.85,"y":27.81}},{"id":"kvg:0589c-s7","start":{"x":60.08,"y":28.72}},{"id":"kvg:0589c-s8","start":{"x":58.91,"y":35.33}},{"id":"kvg:0589c-s9","start":{"x":60.38,"y":39.32}},{"id":"kvg:0589c-s10","start":{"x":64.08,"y":47.03}},{"id":"kvg:0589c-s11","start":{"x":79.58,"y":32.38}},{"id":"kvg:0589c-s12","start":{"x":68.33,"y":45.62}},{"id":"kvg:0589c-s13","start":{"x":29.6,"y":82.17}},{"id":"kvg:0589c-s14","start":{"x":53.27,"y":70.37}},{"id":"kvg:0589c-s15","start":{"x":19.13,"y":94.98}}]