[{"id":"kvg:05b32-s1","start":{"x":13.81,"y":17.77}},{"id":"kvg:05b32-s2","start":{"x":14.71,"y":19.04}},{"id":"kvg:05b32-s3","start":{"x":27.01,"y":19.28}},{"id":"kvg:05b32-s4","start":{"x":15.98,"y":30.1}},{"id":"kvg:05b32-s5","start":{"x":18.1,"y":42.81}},{"id":"kvg:05b32-s6","start":{"x":12.2,"y":58.28}},{"id":"kvg:05b32-s7","start":{"x":26.67,"y":44.86}},{"id":"kvg:05b32-s8","start":{"x":55.09,"y":14.87}},{"id":"kvg:05b32-s9","start":{"x":63.77,"y":33.39}},{"id":"kvg:05b32-s10","start":{"x":43,"y":41.34}},{"id":"kvg:05b32-s11","start":{"x":69.31,"y":16.27}},{"id":"kvg:05b32-s12","start":{"x":70.21,"y":17.54}},{"id":"kvg:05b32-s13","start":{"x":82.51,"y":17.78}},{"id":"kvg:05b32-s14","start":{"x":71.48,"y":28.6}},{"id":"kvg:05b32-s15","start":{"x":73.6,"y":41.31}},{"id":"kvg:05b32-s16","start":{"x":67.2,"y":56.28}},{"id":"kvg:05b32-s17","start":{"x":82.16,"y":44.86}}]