[{"id":"kvg:05c50-s1","start":{"x":23.68,"y":16.15}},{"id":"kvg:05c50-s2","start":{"x":26.9,"y":30.17}},{"id":"kvg:05c50-s3","start":{"x":27.08,"y":17.33}},{"id":"kvg:05c50-s4","start":{"x":45.52,"y":35}},{"id":"kvg:05c50-s5","start":{"x":46.11,"y":49.33}},{"id":"kvg:05c50-s6","start":{"x":38.7,"y":65.39}},{"id":"kvg:05c50-s7","start":{"x":48.85,"y":45.82}},{"id":"kvg:05c50-s8","start":{"x":64.31,"y":31.88}},{"id":"kvg:05c50-s9","start":{"x":51.54,"y":60.38}},{"id":"kvg:05c50-s10","start":{"x":53.13,"y":65.88}}]