[{"id":"kvg:05da2-s1","start":{"x":22.56,"y":20.26}},{"id":"kvg:05da2-s2","start":{"x":11.77,"y":45.13}},{"id":"kvg:05da2-s3","start":{"x":37.29,"y":41.52}},{"id":"kvg:05da2-s4","start":{"x":50.86,"y":22.02}},{"id":"kvg:05da2-s5","start":{"x":66.37,"y":10.37}},{"id":"kvg:05da2-s6","start":{"x":45.51,"y":33.07}},{"id":"kvg:05da2-s7","start":{"x":44.19,"y":47.64}},{"id":"kvg:05da2-s8","start":{"x":53.13,"y":39}},{"id":"kvg:05da2-s9","start":{"x":44.09,"y":61.41}},{"id":"kvg:05da2-s10","start":{"x":69.11,"y":45.53}},{"id":"kvg:05da2-s11","start":{"x":80.21,"y":36.62}},{"id":"kvg:05da2-s12","start":{"x":67.27,"y":57.73}},{"id":"kvg:05da2-s13","start":{"x":44.77,"y":71.31}},{"id":"kvg:05da2-s14","start":{"x":58.79,"y":74}},{"id":"kvg:05da2-s15","start":{"x":71.59,"y":71.41}}]