[{"id":"kvg:06155-s1","start":{"x":22.5,"y":20.06}},{"id":"kvg:06155-s2","start":{"x":38,"y":10.74}},{"id":"kvg:06155-s3","start":{"x":66.57,"y":9.5}},{"id":"kvg:06155-s4","start":{"x":32.27,"y":31.21}},{"id":"kvg:06155-s5","start":{"x":34.45,"y":32.78}},{"id":"kvg:06155-s6","start":{"x":36.17,"y":40.63}},{"id":"kvg:06155-s7","start":{"x":37.83,"y":48.84}},{"id":"kvg:06155-s8","start":{"x":15.38,"y":62.55}},{"id":"kvg:06155-s9","start":{"x":47.91,"y":50.93}},{"id":"kvg:06155-s10","start":{"x":59.25,"y":56.1}},{"id":"kvg:06155-s11","start":{"x":48.38,"y":70.35}},{"id":"kvg:06155-s12","start":{"x":36.62,"y":81.38}},{"id":"kvg:06155-s13","start":{"x":58.84,"y":79.57}},{"id":"kvg:06155-s14","start":{"x":73.28,"y":80.53}}]