[{"id":"kvg:064fa-s1","start":{"x":11,"y":35.42}},{"id":"kvg:064fa-s2","start":{"x":25.72,"y":13}},{"id":"kvg:064fa-s3","start":{"x":10,"y":65.49}},{"id":"kvg:064fa-s4","start":{"x":43.27,"y":15.01}},{"id":"kvg:064fa-s5","start":{"x":44.9,"y":16.94}},{"id":"kvg:064fa-s6","start":{"x":59.44,"y":15.35}},{"id":"kvg:064fa-s7","start":{"x":75.96,"y":14.16}},{"id":"kvg:064fa-s8","start":{"x":47.35,"y":30.2}},{"id":"kvg:064fa-s9","start":{"x":52.99,"y":35}},{"id":"kvg:064fa-s10","start":{"x":60.96,"y":40.62}},{"id":"kvg:064fa-s11","start":{"x":44.91,"y":57.68}},{"id":"kvg:064fa-s12","start":{"x":46.33,"y":59}},{"id":"kvg:064fa-s13","start":{"x":46.33,"y":68.96}},{"id":"kvg:064fa-s14","start":{"x":46.69,"y":78.67}},{"id":"kvg:064fa-s15","start":{"x":91.53,"y":36.7}},{"id":"kvg:064fa-s16","start":{"x":74.47,"y":34.18}},{"id":"kvg:064fa-s17","start":{"x":93.64,"y":67.59}},{"id":"kvg:064fa-s18","start":{"x":74.65,"y":64.37}}]