[{"id":"kvg:0669d-s1","start":{"x":12.77,"y":25.54}},{"id":"kvg:0669d-s2","start":{"x":14.09,"y":27.26}},{"id":"kvg:0669d-s3","start":{"x":13.52,"y":52.65}},{"id":"kvg:0669d-s4","start":{"x":13.86,"y":79.4}},{"id":"kvg:0669d-s5","start":{"x":44.29,"y":15.33}},{"id":"kvg:0669d-s6","start":{"x":43.64,"y":18.9}},{"id":"kvg:0669d-s7","start":{"x":50.2,"y":29.78}},{"id":"kvg:0669d-s8","start":{"x":51.67,"y":30.94}},{"id":"kvg:0669d-s9","start":{"x":53.19,"y":42.22}},{"id":"kvg:0669d-s10","start":{"x":53.67,"y":54.54}},{"id":"kvg:0669d-s11","start":{"x":65.88,"y":59.2}},{"id":"kvg:0669d-s12","start":{"x":39.37,"y":71.82}},{"id":"kvg:0669d-s13","start":{"x":58.14,"y":79.73}},{"id":"kvg:0669d-s14","start":{"x":76.92,"y":81.08}}]