[{"id":"kvg:06baf-s1","start":{"x":14.75,"y":21.47}},{"id":"kvg:06baf-s2","start":{"x":26.99,"y":23.39}},{"id":"kvg:06baf-s3","start":{"x":26.64,"y":40}},{"id":"kvg:06baf-s4","start":{"x":21.46,"y":55.73}},{"id":"kvg:06baf-s5","start":{"x":67.65,"y":11.05}},{"id":"kvg:06baf-s6","start":{"x":50.74,"y":22.14}},{"id":"kvg:06baf-s7","start":{"x":51.06,"y":24.2}},{"id":"kvg:06baf-s8","start":{"x":54.58,"y":32.31}},{"id":"kvg:06baf-s9","start":{"x":68.48,"y":34.61}},{"id":"kvg:06baf-s10","start":{"x":55.45,"y":40.54}},{"id":"kvg:06baf-s11","start":{"x":85.42,"y":38.3}},{"id":"kvg:06baf-s12","start":{"x":56.05,"y":56.98}},{"id":"kvg:06baf-s13","start":{"x":58.01,"y":56.97}},{"id":"kvg:06baf-s14","start":{"x":58.27,"y":65.47}},{"id":"kvg:06baf-s15","start":{"x":57.49,"y":73.58}},{"id":"kvg:06baf-s16","start":{"x":57.14,"y":83.3}},{"id":"kvg:06baf-s17","start":{"x":63.08,"y":87.34}},{"id":"kvg:06baf-s18","start":{"x":79.5,"y":87.86}}]