[{"id":"kvg:06dee-s1","start":{"x":18.63,"y":16}},{"id":"kvg:06dee-s2","start":{"x":12,"y":39.5}},{"id":"kvg:06dee-s3","start":{"x":14.75,"y":89.23}},{"id":"kvg:06dee-s4","start":{"x":54.89,"y":13}},{"id":"kvg:06dee-s5","start":{"x":47.11,"y":34.67}},{"id":"kvg:06dee-s6","start":{"x":76.17,"y":12.76}},{"id":"kvg:06dee-s7","start":{"x":48.27,"y":37}},{"id":"kvg:06dee-s8","start":{"x":69.05,"y":36.91}},{"id":"kvg:06dee-s9","start":{"x":49.44,"y":53.84}},{"id":"kvg:06dee-s10","start":{"x":48.44,"y":71.65}},{"id":"kvg:06dee-s11","start":{"x":48.44,"y":93.78}}]