[{"id":"kvg:0723a-s1","start":{"x":41.52,"y":11.68}},{"id":"kvg:0723a-s2","start":{"x":64.5,"y":11.21}},{"id":"kvg:0723a-s3","start":{"x":65.88,"y":18.16}},{"id":"kvg:0723a-s4","start":{"x":39,"y":22.25}},{"id":"kvg:0723a-s5","start":{"x":23.27,"y":52.57}},{"id":"kvg:0723a-s6","start":{"x":27.76,"y":53.13}},{"id":"kvg:0723a-s7","start":{"x":29.26,"y":62.66}},{"id":"kvg:0723a-s8","start":{"x":29,"y":72.22}},{"id":"kvg:0723a-s9","start":{"x":17.84,"y":88.6}},{"id":"kvg:0723a-s10","start":{"x":45.94,"y":51.43}},{"id":"kvg:0723a-s11","start":{"x":59.54,"y":51.39}},{"id":"kvg:0723a-s12","start":{"x":75.04,"y":65.67}},{"id":"kvg:0723a-s13","start":{"x":63.62,"y":51.77}}]