[{"id":"kvg:0734e-s1","start":{"x":37.4,"y":9.68}},{"id":"kvg:0734e-s2","start":{"x":21.7,"y":11.6}},{"id":"kvg:0734e-s3","start":{"x":15.64,"y":38.97}},{"id":"kvg:0734e-s4","start":{"x":26.87,"y":41.31}},{"id":"kvg:0734e-s5","start":{"x":66.76,"y":8}},{"id":"kvg:0734e-s6","start":{"x":63.94,"y":15}},{"id":"kvg:0734e-s7","start":{"x":62.85,"y":18.79}},{"id":"kvg:0734e-s8","start":{"x":54.98,"y":25.42}},{"id":"kvg:0734e-s9","start":{"x":44.1,"y":40.15}},{"id":"kvg:0734e-s10","start":{"x":79.06,"y":27.29}},{"id":"kvg:0734e-s11","start":{"x":56.01,"y":45.52}},{"id":"kvg:0734e-s12","start":{"x":17.27,"y":74.64}},{"id":"kvg:0734e-s13","start":{"x":53.06,"y":56.75}},{"id":"kvg:0734e-s14","start":{"x":56.26,"y":73.65}},{"id":"kvg:0734e-s15","start":{"x":64.91,"y":59.93}}]