[{"id":"kvg:078cb-s1","start":{"x":13.38,"y":23.48}},{"id":"kvg:078cb-s2","start":{"x":25.49,"y":25}},{"id":"kvg:078cb-s3","start":{"x":19.04,"y":48.73}},{"id":"kvg:078cb-s4","start":{"x":21.73,"y":51}},{"id":"kvg:078cb-s5","start":{"x":21.83,"y":78.09}},{"id":"kvg:078cb-s6","start":{"x":52.45,"y":12.83}},{"id":"kvg:078cb-s7","start":{"x":83.82,"y":10.52}},{"id":"kvg:078cb-s8","start":{"x":45.38,"y":29.29}},{"id":"kvg:078cb-s9","start":{"x":66.57,"y":27.93}},{"id":"kvg:078cb-s10","start":{"x":46.68,"y":42.07}},{"id":"kvg:078cb-s11","start":{"x":44.04,"y":55.8}},{"id":"kvg:078cb-s12","start":{"x":57.73,"y":57.52}},{"id":"kvg:078cb-s13","start":{"x":56.03,"y":70.47}},{"id":"kvg:078cb-s14","start":{"x":70.03,"y":72.04}},{"id":"kvg:078cb-s15","start":{"x":46.75,"y":95.32}}]