[{"id":"kvg:07b0b-s1","start":{"x":32,"y":9.25}},{"id":"kvg:07b0b-s2","start":{"x":29.73,"y":23.79}},{"id":"kvg:07b0b-s3","start":{"x":35.52,"y":26.33}},{"id":"kvg:07b0b-s4","start":{"x":65.23,"y":9.5}},{"id":"kvg:07b0b-s5","start":{"x":64.73,"y":22.32}},{"id":"kvg:07b0b-s6","start":{"x":76.71,"y":24.29}},{"id":"kvg:07b0b-s7","start":{"x":27.07,"y":43.89}},{"id":"kvg:07b0b-s8","start":{"x":14.7,"y":58.04}},{"id":"kvg:07b0b-s9","start":{"x":26.5,"y":71.72}},{"id":"kvg:07b0b-s10","start":{"x":52.97,"y":45.01}}]