[{"id":"kvg:07e4b-s1","start":{"x":17.06,"y":18.32}},{"id":"kvg:07e4b-s2","start":{"x":19.49,"y":25.2}},{"id":"kvg:07e4b-s3","start":{"x":21.18,"y":26.44}},{"id":"kvg:07e4b-s4","start":{"x":22.76,"y":32.49}},{"id":"kvg:07e4b-s5","start":{"x":24.01,"y":38.79}},{"id":"kvg:07e4b-s6","start":{"x":13.22,"y":47.36}},{"id":"kvg:07e4b-s7","start":{"x":33.39,"y":10.63}},{"id":"kvg:07e4b-s8","start":{"x":60.5,"y":12.31}},{"id":"kvg:07e4b-s9","start":{"x":62.15,"y":13.51}},{"id":"kvg:07e4b-s10","start":{"x":58.45,"y":34.52}},{"id":"kvg:07e4b-s11","start":{"x":58.85,"y":39.89}},{"id":"kvg:07e4b-s12","start":{"x":50.62,"y":54.5}},{"id":"kvg:07e4b-s13","start":{"x":67.75,"y":56.7}},{"id":"kvg:07e4b-s14","start":{"x":70.75,"y":69.15}},{"id":"kvg:07e4b-s15","start":{"x":54,"y":80.99}},{"id":"kvg:07e4b-s16","start":{"x":41.95,"y":87.57}},{"id":"kvg:07e4b-s17","start":{"x":69.16,"y":85.83}}]