[{"id":"kvg:07f60-s1","start":{"x":21.89,"y":14.07}},{"id":"kvg:07f60-s2","start":{"x":23.72,"y":15.31}},{"id":"kvg:07f60-s3","start":{"x":43.76,"y":14.86}},{"id":"kvg:07f60-s4","start":{"x":63.95,"y":13.29}},{"id":"kvg:07f60-s5","start":{"x":26.15,"y":29.39}},{"id":"kvg:07f60-s6","start":{"x":23.5,"y":39.25}},{"id":"kvg:07f60-s7","start":{"x":27.1,"y":54.46}},{"id":"kvg:07f60-s8","start":{"x":26.5,"y":40.25}},{"id":"kvg:07f60-s9","start":{"x":28,"y":66.5}},{"id":"kvg:07f60-s10","start":{"x":52.5,"y":52.5}}]