[{"id":"kvg:08006-s1","start":{"x":27.75,"y":26.47}},{"id":"kvg:08006-s2","start":{"x":47.17,"y":12.12}},{"id":"kvg:08006-s3","start":{"x":13.5,"y":40.79}},{"id":"kvg:08006-s4","start":{"x":79.34,"y":14.88}},{"id":"kvg:08006-s5","start":{"x":71.84,"y":41.5}},{"id":"kvg:08006-s6","start":{"x":37.85,"y":44.92}},{"id":"kvg:08006-s7","start":{"x":36.52,"y":68.69}},{"id":"kvg:08006-s8","start":{"x":38.44,"y":70.32}},{"id":"kvg:08006-s9","start":{"x":39.33,"y":81.98}},{"id":"kvg:08006-s10","start":{"x":42.19,"y":95.31}}]