[{"id":"kvg:08548-s1","start":{"x":17,"y":19.82}},{"id":"kvg:08548-s2","start":{"x":36.84,"y":9.5}},{"id":"kvg:08548-s3","start":{"x":67.19,"y":8.25}},{"id":"kvg:08548-s4","start":{"x":23.89,"y":30.36}},{"id":"kvg:08548-s5","start":{"x":22.25,"y":38.97}},{"id":"kvg:08548-s6","start":{"x":23.42,"y":40.32}},{"id":"kvg:08548-s7","start":{"x":42.59,"y":30.76}},{"id":"kvg:08548-s8","start":{"x":65.51,"y":31.17}},{"id":"kvg:08548-s9","start":{"x":26.15,"y":49.63}},{"id":"kvg:08548-s10","start":{"x":30.28,"y":56.22}},{"id":"kvg:08548-s11","start":{"x":30.92,"y":57.21}},{"id":"kvg:08548-s12","start":{"x":32.89,"y":65.87}},{"id":"kvg:08548-s13","start":{"x":33.99,"y":75.04}},{"id":"kvg:08548-s14","start":{"x":16.05,"y":85.93}},{"id":"kvg:08548-s15","start":{"x":54.54,"y":75.69}}]