[{"id":"kvg:085ab-s1","start":{"x":21.01,"y":23.51}},{"id":"kvg:085ab-s2","start":{"x":38.14,"y":13.66}},{"id":"kvg:085ab-s3","start":{"x":68.75,"y":11}},{"id":"kvg:085ab-s4","start":{"x":60.95,"y":27.17}},{"id":"kvg:085ab-s5","start":{"x":17.19,"y":42.17}},{"id":"kvg:085ab-s6","start":{"x":30.53,"y":48.22}},{"id":"kvg:085ab-s7","start":{"x":32.4,"y":49.63}},{"id":"kvg:085ab-s8","start":{"x":34.31,"y":56.23}},{"id":"kvg:085ab-s9","start":{"x":35.93,"y":64.23}},{"id":"kvg:085ab-s10","start":{"x":53.35,"y":34.63}},{"id":"kvg:085ab-s11","start":{"x":35.77,"y":70.9}},{"id":"kvg:085ab-s12","start":{"x":25.46,"y":80.87}},{"id":"kvg:085ab-s13","start":{"x":23.9,"y":87.67}},{"id":"kvg:085ab-s14","start":{"x":40.12,"y":86.6}},{"id":"kvg:085ab-s15","start":{"x":61.26,"y":85.83}},{"id":"kvg:085ab-s16","start":{"x":82.09,"y":86.01}}]