[{"id":"kvg:085cd-s1","start":{"x":18.75,"y":22.69}},{"id":"kvg:085cd-s2","start":{"x":38.19,"y":12.2}},{"id":"kvg:085cd-s3","start":{"x":68.17,"y":10.67}},{"id":"kvg:085cd-s4","start":{"x":23.41,"y":37.47}},{"id":"kvg:085cd-s5","start":{"x":24.81,"y":37.94}},{"id":"kvg:085cd-s6","start":{"x":36.53,"y":38.06}},{"id":"kvg:085cd-s7","start":{"x":25.99,"y":47.81}},{"id":"kvg:085cd-s8","start":{"x":25.77,"y":56.86}},{"id":"kvg:085cd-s9","start":{"x":36.84,"y":56.83}},{"id":"kvg:085cd-s10","start":{"x":25.56,"y":66.73}},{"id":"kvg:085cd-s11","start":{"x":67.27,"y":32.75}},{"id":"kvg:085cd-s12","start":{"x":65,"y":43.57}},{"id":"kvg:085cd-s13","start":{"x":61,"y":58.52}},{"id":"kvg:085cd-s14","start":{"x":28.21,"y":74.33}},{"id":"kvg:085cd-s15","start":{"x":30.1,"y":76.23}},{"id":"kvg:085cd-s16","start":{"x":44.86,"y":76.69}},{"id":"kvg:085cd-s17","start":{"x":63.54,"y":75.26}},{"id":"kvg:085cd-s18","start":{"x":14.5,"y":95.3}}]