[{"id":"kvg:0879f-s1","start":{"x":10.76,"y":33.4}},{"id":"kvg:0879f-s2","start":{"x":12.72,"y":34.98}},{"id":"kvg:0879f-s3","start":{"x":14.76,"y":59.93}},{"id":"kvg:0879f-s4","start":{"x":22.42,"y":13.25}},{"id":"kvg:0879f-s5","start":{"x":11.57,"y":86.27}},{"id":"kvg:0879f-s6","start":{"x":33.5,"y":66.75}},{"id":"kvg:0879f-s7","start":{"x":48.67,"y":18.32}},{"id":"kvg:0879f-s8","start":{"x":48.06,"y":22.17}},{"id":"kvg:0879f-s9","start":{"x":53.21,"y":32.86}},{"id":"kvg:0879f-s10","start":{"x":54.68,"y":34.49}},{"id":"kvg:0879f-s11","start":{"x":56.2,"y":46.51}},{"id":"kvg:0879f-s12","start":{"x":56.69,"y":57.53}},{"id":"kvg:0879f-s13","start":{"x":68.54,"y":61.5}},{"id":"kvg:0879f-s14","start":{"x":44.54,"y":71.45}},{"id":"kvg:0879f-s15","start":{"x":62.77,"y":76.49}},{"id":"kvg:0879f-s16","start":{"x":79.8,"y":77.86}}]