[{"id":"kvg:0894d-s1","start":{"x":19.58,"y":15}},{"id":"kvg:0894d-s2","start":{"x":11.2,"y":36.36}},{"id":"kvg:0894d-s3","start":{"x":26,"y":52.61}},{"id":"kvg:0894d-s4","start":{"x":39.79,"y":48.89}},{"id":"kvg:0894d-s5","start":{"x":31.58,"y":61.25}},{"id":"kvg:0894d-s6","start":{"x":56.01,"y":14.24}},{"id":"kvg:0894d-s7","start":{"x":52.86,"y":29.73}},{"id":"kvg:0894d-s8","start":{"x":74.16,"y":13.75}},{"id":"kvg:0894d-s9","start":{"x":53.06,"y":29.71}},{"id":"kvg:0894d-s10","start":{"x":69.28,"y":29.42}},{"id":"kvg:0894d-s11","start":{"x":53.78,"y":38.44}},{"id":"kvg:0894d-s12","start":{"x":53,"y":46.19}},{"id":"kvg:0894d-s13","start":{"x":53.53,"y":54.79}},{"id":"kvg:0894d-s14","start":{"x":45.5,"y":67.63}},{"id":"kvg:0894d-s15","start":{"x":68.78,"y":58.25}},{"id":"kvg:0894d-s16","start":{"x":69.4,"y":67.41}},{"id":"kvg:0894d-s17","start":{"x":70.66,"y":67.25}}]