[{"id":"kvg:089a1-s1","start":{"x":11.02,"y":24.45}},{"id":"kvg:089a1-s2","start":{"x":29.03,"y":23.75}},{"id":"kvg:089a1-s3","start":{"x":19.25,"y":35.49}},{"id":"kvg:089a1-s4","start":{"x":18.97,"y":49.36}},{"id":"kvg:089a1-s5","start":{"x":44.18,"y":34.74}},{"id":"kvg:089a1-s6","start":{"x":42.83,"y":47.21}},{"id":"kvg:089a1-s7","start":{"x":12.1,"y":82.99}},{"id":"kvg:089a1-s8","start":{"x":57.69,"y":18.69}},{"id":"kvg:089a1-s9","start":{"x":59.52,"y":20.11}},{"id":"kvg:089a1-s10","start":{"x":58.98,"y":33.42}},{"id":"kvg:089a1-s11","start":{"x":59.19,"y":46.82}},{"id":"kvg:089a1-s12","start":{"x":58.84,"y":61.69}},{"id":"kvg:089a1-s13","start":{"x":64.25,"y":65.25}},{"id":"kvg:089a1-s14","start":{"x":74.86,"y":63.47}}]