[{"id":"kvg:08c6a-s1","start":{"x":54.64,"y":9.86}},{"id":"kvg:08c6a-s2","start":{"x":27.23,"y":21.67}},{"id":"kvg:08c6a-s3","start":{"x":39.75,"y":27.51}},{"id":"kvg:08c6a-s4","start":{"x":41.6,"y":28.38}},{"id":"kvg:08c6a-s5","start":{"x":44,"y":36.15}},{"id":"kvg:08c6a-s6","start":{"x":24.88,"y":42}},{"id":"kvg:08c6a-s7","start":{"x":26.24,"y":46.24}},{"id":"kvg:08c6a-s8","start":{"x":34.1,"y":53.01}},{"id":"kvg:08c6a-s9","start":{"x":53.04,"y":55.47}},{"id":"kvg:08c6a-s10","start":{"x":51.76,"y":60.34}},{"id":"kvg:08c6a-s11","start":{"x":51.38,"y":65}},{"id":"kvg:08c6a-s12","start":{"x":53.96,"y":74.44}},{"id":"kvg:08c6a-s13","start":{"x":73.79,"y":57.28}},{"id":"kvg:08c6a-s14","start":{"x":58.43,"y":70.72}}]