[{"id":"kvg:08d6d-s1","start":{"x":14.76,"y":30.73}},{"id":"kvg:08d6d-s2","start":{"x":27.53,"y":15.2}},{"id":"kvg:08d6d-s3","start":{"x":9.63,"y":45.17}},{"id":"kvg:08d6d-s4","start":{"x":25.05,"y":46.89}},{"id":"kvg:08d6d-s5","start":{"x":34.82,"y":45.58}},{"id":"kvg:08d6d-s6","start":{"x":16.98,"y":56.89}},{"id":"kvg:08d6d-s7","start":{"x":41.62,"y":57.58}},{"id":"kvg:08d6d-s8","start":{"x":54.52,"y":29.5}},{"id":"kvg:08d6d-s9","start":{"x":67.96,"y":11.37}},{"id":"kvg:08d6d-s10","start":{"x":49.06,"y":46.21}},{"id":"kvg:08d6d-s11","start":{"x":93.74,"y":18.82}},{"id":"kvg:08d6d-s12","start":{"x":81.05,"y":48.25}},{"id":"kvg:08d6d-s13","start":{"x":63.79,"y":62.63}},{"id":"kvg:08d6d-s14","start":{"x":64.38,"y":64.16}},{"id":"kvg:08d6d-s15","start":{"x":64.71,"y":76.96}},{"id":"kvg:08d6d-s16","start":{"x":64.61,"y":92.96}}]