[{"id":"kvg:08e0f-s1","start":{"x":15.03,"y":23.63}},{"id":"kvg:08e0f-s2","start":{"x":16.68,"y":24.48}},{"id":"kvg:08e0f-s3","start":{"x":20.5,"y":40.94}},{"id":"kvg:08e0f-s4","start":{"x":29.62,"y":41.74}},{"id":"kvg:08e0f-s5","start":{"x":31.88,"y":56.49}},{"id":"kvg:08e0f-s6","start":{"x":18.12,"y":57.99}},{"id":"kvg:08e0f-s7","start":{"x":13,"y":86.07}},{"id":"kvg:08e0f-s8","start":{"x":68.62,"y":14.83}},{"id":"kvg:08e0f-s9","start":{"x":46.9,"y":31.79}},{"id":"kvg:08e0f-s10","start":{"x":87.95,"y":21.26}},{"id":"kvg:08e0f-s11","start":{"x":71.02,"y":28.91}},{"id":"kvg:08e0f-s12","start":{"x":53.34,"y":59.97}},{"id":"kvg:08e0f-s13","start":{"x":55.51,"y":61.44}},{"id":"kvg:08e0f-s14","start":{"x":55.47,"y":76.58}},{"id":"kvg:08e0f-s15","start":{"x":55.6,"y":92.62}}]