[{"id":"kvg:08e5f-s1","start":{"x":17.03,"y":20.84}},{"id":"kvg:08e5f-s2","start":{"x":18.91,"y":22.4}},{"id":"kvg:08e5f-s3","start":{"x":21.95,"y":38.98}},{"id":"kvg:08e5f-s4","start":{"x":30.62,"y":39.24}},{"id":"kvg:08e5f-s5","start":{"x":32.88,"y":55.74}},{"id":"kvg:08e5f-s6","start":{"x":18.87,"y":57.49}},{"id":"kvg:08e5f-s7","start":{"x":14.75,"y":86.82}},{"id":"kvg:08e5f-s8","start":{"x":51.29,"y":21.42}},{"id":"kvg:08e5f-s9","start":{"x":67.27,"y":11.88}},{"id":"kvg:08e5f-s10","start":{"x":50.27,"y":32.06}},{"id":"kvg:08e5f-s11","start":{"x":44.06,"y":43.49}},{"id":"kvg:08e5f-s12","start":{"x":53.29,"y":50.96}},{"id":"kvg:08e5f-s13","start":{"x":54.84,"y":52.2}},{"id":"kvg:08e5f-s14","start":{"x":55.29,"y":60.95}},{"id":"kvg:08e5f-s15","start":{"x":55.02,"y":69.58}},{"id":"kvg:08e5f-s16","start":{"x":55.5,"y":79.05}},{"id":"kvg:08e5f-s17","start":{"x":61.96,"y":84.77}},{"id":"kvg:08e5f-s18","start":{"x":77.47,"y":84.21}}]