[{"id":"kvg:0901d-s1","start":{"x":38.55,"y":35.02}},{"id":"kvg:0901d-s2","start":{"x":51.13,"y":16.38}},{"id":"kvg:0901d-s3","start":{"x":38.25,"y":57.73}},{"id":"kvg:0901d-s4","start":{"x":86.63,"y":16.42}},{"id":"kvg:0901d-s5","start":{"x":67.49,"y":28.68}},{"id":"kvg:0901d-s6","start":{"x":70.31,"y":41.98}},{"id":"kvg:0901d-s7","start":{"x":82.08,"y":43.47}},{"id":"kvg:0901d-s8","start":{"x":20.12,"y":18.88}},{"id":"kvg:0901d-s9","start":{"x":13,"y":50.5}},{"id":"kvg:0901d-s10","start":{"x":15.25,"y":83.25}}]