[{"id":"kvg:0903c-s1","start":{"x":47.26,"y":17.04}},{"id":"kvg:0903c-s2","start":{"x":47.23,"y":28.41}},{"id":"kvg:0903c-s3","start":{"x":49.45,"y":30.26}},{"id":"kvg:0903c-s4","start":{"x":52.03,"y":42.22}},{"id":"kvg:0903c-s5","start":{"x":44.11,"y":53.56}},{"id":"kvg:0903c-s6","start":{"x":45.52,"y":55.06}},{"id":"kvg:0903c-s7","start":{"x":64.33,"y":53.62}},{"id":"kvg:0903c-s8","start":{"x":47.91,"y":66.65}},{"id":"kvg:0903c-s9","start":{"x":48.94,"y":80.54}},{"id":"kvg:0903c-s10","start":{"x":22.71,"y":16.5}},{"id":"kvg:0903c-s11","start":{"x":15.96,"y":39}},{"id":"kvg:0903c-s12","start":{"x":14.5,"y":60.94}},{"id":"kvg:0903c-s13","start":{"x":15.75,"y":88.07}}]