[{"id":"kvg:09075-s1","start":{"x":47.9,"y":12.08}},{"id":"kvg:09075-s2","start":{"x":74.17,"y":9.4}},{"id":"kvg:09075-s3","start":{"x":38.78,"y":25.3}},{"id":"kvg:09075-s4","start":{"x":47.01,"y":35.48}},{"id":"kvg:09075-s5","start":{"x":48.72,"y":37.01}},{"id":"kvg:09075-s6","start":{"x":57.4,"y":27.94}},{"id":"kvg:09075-s7","start":{"x":66.97,"y":27}},{"id":"kvg:09075-s8","start":{"x":49.39,"y":51.45}},{"id":"kvg:09075-s9","start":{"x":48.94,"y":59.07}},{"id":"kvg:09075-s10","start":{"x":37.93,"y":69.92}},{"id":"kvg:09075-s11","start":{"x":74.63,"y":61.48}},{"id":"kvg:09075-s12","start":{"x":53.88,"y":75}},{"id":"kvg:09075-s13","start":{"x":16.88,"y":21.88}},{"id":"kvg:09075-s14","start":{"x":13.5,"y":54.58}},{"id":"kvg:09075-s15","start":{"x":13,"y":85.58}}]