[{"id":"kvg:091c9-s1","start":{"x":43.75,"y":12.14}},{"id":"kvg:091c9-s2","start":{"x":16.67,"y":31.19}},{"id":"kvg:091c9-s3","start":{"x":48.19,"y":25.3}},{"id":"kvg:091c9-s4","start":{"x":11.5,"y":47.45}},{"id":"kvg:091c9-s5","start":{"x":31.91,"y":23.29}},{"id":"kvg:091c9-s6","start":{"x":32.66,"y":46.65}},{"id":"kvg:091c9-s7","start":{"x":36.31,"y":54.61}},{"id":"kvg:091c9-s8","start":{"x":55.25,"y":41.85}},{"id":"kvg:091c9-s9","start":{"x":57.68,"y":44.34}},{"id":"kvg:091c9-s10","start":{"x":73.36,"y":16.36}},{"id":"kvg:091c9-s11","start":{"x":58.64,"y":65.96}},{"id":"kvg:091c9-s12","start":{"x":60.12,"y":91.9}}]