[{"id":"kvg:09323-s1","start":{"x":28.75,"y":14.24}},{"id":"kvg:09323-s2","start":{"x":29.39,"y":19.46}},{"id":"kvg:09323-s3","start":{"x":18,"y":40.07}},{"id":"kvg:09323-s4","start":{"x":12.09,"y":53.81}},{"id":"kvg:09323-s5","start":{"x":26.95,"y":40.19}},{"id":"kvg:09323-s6","start":{"x":14.64,"y":63.51}},{"id":"kvg:09323-s7","start":{"x":39.2,"y":59.05}},{"id":"kvg:09323-s8","start":{"x":11.5,"y":89.39}},{"id":"kvg:09323-s9","start":{"x":46.6,"y":22.23}},{"id":"kvg:09323-s10","start":{"x":51.29,"y":29.7}},{"id":"kvg:09323-s11","start":{"x":72.18,"y":20.59}},{"id":"kvg:09323-s12","start":{"x":74.1,"y":29.46}},{"id":"kvg:09323-s13","start":{"x":47.28,"y":59.17}},{"id":"kvg:09323-s14","start":{"x":48.06,"y":67.09}},{"id":"kvg:09323-s15","start":{"x":72.56,"y":56.94}},{"id":"kvg:09323-s16","start":{"x":73.16,"y":63.66}}]