[{"id":"kvg:09332-s1","start":{"x":30,"y":13.74}},{"id":"kvg:09332-s2","start":{"x":32.53,"y":20.3}},{"id":"kvg:09332-s3","start":{"x":21,"y":40}},{"id":"kvg:09332-s4","start":{"x":12.59,"y":55.23}},{"id":"kvg:09332-s5","start":{"x":29.45,"y":40.94}},{"id":"kvg:09332-s6","start":{"x":16.38,"y":65.62}},{"id":"kvg:09332-s7","start":{"x":41.54,"y":60.3}},{"id":"kvg:09332-s8","start":{"x":14.25,"y":88}},{"id":"kvg:09332-s9","start":{"x":50.53,"y":17.5}},{"id":"kvg:09332-s10","start":{"x":52.25,"y":30.75}},{"id":"kvg:09332-s11","start":{"x":45.39,"y":45.68}},{"id":"kvg:09332-s12","start":{"x":67.27,"y":46.58}},{"id":"kvg:09332-s13","start":{"x":49.75,"y":58.25}},{"id":"kvg:09332-s14","start":{"x":43.64,"y":87.14}},{"id":"kvg:09332-s15","start":{"x":87.78,"y":51.64}},{"id":"kvg:09332-s16","start":{"x":74.25,"y":70.25}}]