[{"id":"kvg:093e4-s1","start":{"x":30.25,"y":13.74}},{"id":"kvg:093e4-s2","start":{"x":30.64,"y":20.21}},{"id":"kvg:093e4-s3","start":{"x":20,"y":40.5}},{"id":"kvg:093e4-s4","start":{"x":12.09,"y":54.31}},{"id":"kvg:093e4-s5","start":{"x":27.95,"y":40.69}},{"id":"kvg:093e4-s6","start":{"x":13.89,"y":65.51}},{"id":"kvg:093e4-s7","start":{"x":40.67,"y":60.55}},{"id":"kvg:093e4-s8","start":{"x":11.5,"y":91.35}},{"id":"kvg:093e4-s9","start":{"x":52.31,"y":20.75}},{"id":"kvg:093e4-s10","start":{"x":53.65,"y":21.55}},{"id":"kvg:093e4-s11","start":{"x":45.47,"y":30.41}},{"id":"kvg:093e4-s12","start":{"x":56.07,"y":39.57}},{"id":"kvg:093e4-s13","start":{"x":53.74,"y":47.25}},{"id":"kvg:093e4-s14","start":{"x":54.94,"y":48.24}},{"id":"kvg:093e4-s15","start":{"x":57.4,"y":58.21}},{"id":"kvg:093e4-s16","start":{"x":69.4,"y":12.75}},{"id":"kvg:093e4-s17","start":{"x":67.99,"y":59.48}},{"id":"kvg:093e4-s18","start":{"x":81.64,"y":62.92}},{"id":"kvg:093e4-s19","start":{"x":44.63,"y":71.36}}]