[{"id":"kvg:09771-s1","start":{"x":9.48,"y":25.31}},{"id":"kvg:09771-s2","start":{"x":20.27,"y":15.11}},{"id":"kvg:09771-s3","start":{"x":38.24,"y":12}},{"id":"kvg:09771-s4","start":{"x":24.56,"y":37.24}},{"id":"kvg:09771-s5","start":{"x":14.76,"y":48.7}},{"id":"kvg:09771-s6","start":{"x":16.04,"y":49.85}},{"id":"kvg:09771-s7","start":{"x":18.42,"y":64.55}},{"id":"kvg:09771-s8","start":{"x":10.25,"y":75.99}},{"id":"kvg:09771-s9","start":{"x":30.46,"y":38.25}},{"id":"kvg:09771-s10","start":{"x":57.15,"y":24.4}},{"id":"kvg:09771-s11","start":{"x":71.42,"y":27.33}},{"id":"kvg:09771-s12","start":{"x":53.77,"y":39}}]