[{"id":"kvg:09acf-s1","start":{"x":18.12,"y":16.2}},{"id":"kvg:09acf-s2","start":{"x":19.31,"y":17.63}},{"id":"kvg:09acf-s3","start":{"x":29.07,"y":24.62}},{"id":"kvg:09acf-s4","start":{"x":29.98,"y":26.41}},{"id":"kvg:09acf-s5","start":{"x":12.04,"y":37.62}},{"id":"kvg:09acf-s6","start":{"x":12.19,"y":40.76}},{"id":"kvg:09acf-s7","start":{"x":20.31,"y":48.12}},{"id":"kvg:09acf-s8","start":{"x":21.79,"y":49.32}},{"id":"kvg:09acf-s9","start":{"x":21.79,"y":60.81}},{"id":"kvg:09acf-s10","start":{"x":21.49,"y":73.17}},{"id":"kvg:09acf-s11","start":{"x":55.25,"y":22.54}},{"id":"kvg:09acf-s12","start":{"x":56.52,"y":23.82}},{"id":"kvg:09acf-s13","start":{"x":48.9,"y":31.81}},{"id":"kvg:09acf-s14","start":{"x":59.82,"y":41.48}},{"id":"kvg:09acf-s15","start":{"x":55.11,"y":48.66}},{"id":"kvg:09acf-s16","start":{"x":56.21,"y":49.71}},{"id":"kvg:09acf-s17","start":{"x":58.5,"y":59.68}},{"id":"kvg:09acf-s18","start":{"x":70.99,"y":13.75}},{"id":"kvg:09acf-s19","start":{"x":68.58,"y":61.99}},{"id":"kvg:09acf-s20","start":{"x":81.94,"y":68.06}},{"id":"kvg:09acf-s21","start":{"x":47.63,"y":71.5}}]