[{"id":"kvg:09ebb-s1","start":{"x":52.31,"y":10.88}},{"id":"kvg:09ebb-s2","start":{"x":20.13,"y":26.73}},{"id":"kvg:09ebb-s3","start":{"x":23.74,"y":28.25}},{"id":"kvg:09ebb-s4","start":{"x":29.89,"y":52.37}},{"id":"kvg:09ebb-s5","start":{"x":40.97,"y":36.68}},{"id":"kvg:09ebb-s6","start":{"x":41.02,"y":53.42}},{"id":"kvg:09ebb-s7","start":{"x":44.89,"y":60.68}},{"id":"kvg:09ebb-s8","start":{"x":59.02,"y":48.92}},{"id":"kvg:09ebb-s9","start":{"x":70.99,"y":32.25}},{"id":"kvg:09ebb-s10","start":{"x":71.83,"y":48.9}},{"id":"kvg:09ebb-s11","start":{"x":73.02,"y":50.17}}]